bitcoin_qrreader/__init__.py
bitcoin_qrreader/bitcoin_qr.py
bitcoin_qrreader/bitcoin_qr_gui.py
bitcoin_qrreader/multipath_descriptor.py
bitcoin_qrreader/qr_qui.py
bitcoin_qrreader/ur/LICENSE
bitcoin_qrreader/ur/__init__.py
bitcoin_qrreader/ur/bytewords.py
bitcoin_qrreader/ur/cbor_lite.py
bitcoin_qrreader/ur/constants.py
bitcoin_qrreader/ur/crc32.py
bitcoin_qrreader/ur/fountain_decoder.py
bitcoin_qrreader/ur/fountain_encoder.py
bitcoin_qrreader/ur/fountain_utils.py
bitcoin_qrreader/ur/random_sampler.py
bitcoin_qrreader/ur/ur.py
bitcoin_qrreader/ur/ur_decoder.py
bitcoin_qrreader/ur/ur_encoder.py
bitcoin_qrreader/ur/utils.py
bitcoin_qrreader/ur/xoshiro256.py
bitcoin_qrreader/urtypes/LICENSE.md
bitcoin_qrreader/urtypes/README.md
bitcoin_qrreader/urtypes/__init__.py
bitcoin_qrreader/urtypes/bytes.py
bitcoin_qrreader/urtypes/cbor/COPYING
bitcoin_qrreader/urtypes/cbor/__init__.py
bitcoin_qrreader/urtypes/cbor/data.py
bitcoin_qrreader/urtypes/cbor/decoder.py
bitcoin_qrreader/urtypes/cbor/encoder.py
bitcoin_qrreader/urtypes/crypto/__init__.py
bitcoin_qrreader/urtypes/crypto/account.py
bitcoin_qrreader/urtypes/crypto/bip39.py
bitcoin_qrreader/urtypes/crypto/coin_info.py
bitcoin_qrreader/urtypes/crypto/ec_key.py
bitcoin_qrreader/urtypes/crypto/hd_key.py
bitcoin_qrreader/urtypes/crypto/keypath.py
bitcoin_qrreader/urtypes/crypto/multi_key.py
bitcoin_qrreader/urtypes/crypto/output.py
bitcoin_qrreader/urtypes/crypto/psbt.py
bitcoin_qrreader/urtypes/registry.py
bitcoin_qrreader-0.8.8.dist-info/LICENSE
bitcoin_qrreader-0.8.8.dist-info/METADATA
bitcoin_qrreader-0.8.8.dist-info/WHEEL
bitcoin_qrreader-0.8.8.dist-info/RECORD
