Metadata-Version: 2.1
Name: bitcoin-qrreader
Version: 0.8.8
Summary: A python bitcoin qr reader
Home-page: https://github.com/andreasgriffin/bitcoin-qrreader
License: GPL-3.0
Author: andreasgriffin
Author-email: andreasgriffin@proton.me
Requires-Python: >=3.8,<3.12
Classifier: License :: OSI Approved :: GNU General Public License v3 (GPLv3)
Classifier: Programming Language :: Python :: 3
Classifier: Programming Language :: Python :: 3.8
Classifier: Programming Language :: Python :: 3.9
Classifier: Programming Language :: Python :: 3.10
Classifier: Programming Language :: Python :: 3.11
Requires-Dist: base58 (==2.1.1)
Requires-Dist: bdkpython (==0.31.0)
Requires-Dist: hwi (==2.3.1)
Requires-Dist: mss (==9.0.1)
Requires-Dist: numpy (>=1.21.0,<2.0.0)
Requires-Dist: opencv-python-headless (>=4.9.0.80,<5.0.0.0)
Requires-Dist: pygame (==2.5.2)
Requires-Dist: pyqt6 (>=6.7.0,<7.0.0)
Requires-Dist: pyzbar (==0.1.9)
